datalad_publicneuro/__about__.py
datalad_publicneuro/__init__.py
datalad_publicneuro/annexremotes/__init__.py
datalad_publicneuro/annexremotes/uncurl_publicneuro.py
datalad_publicneuro/tests/__init__.py
datalad_publicneuro/url_operations/__init__.py
datalad_publicneuro/url_operations/publicneuro.py
datalad_publicneuro/url_operations/publicneuro_ca.pem
datalad_publicneuro-0.1.0.dist-info/METADATA
datalad_publicneuro-0.1.0.dist-info/WHEEL
datalad_publicneuro-0.1.0.dist-info/entry_points.txt
datalad_publicneuro-0.1.0.dist-info/licenses/LICENSE
datalad_publicneuro-0.1.0.dist-info/RECORD
