Metadata-Version: 2.4
Name: datalad-publicneuro
Version: 0.1.0
Summary: A DataLad extension that simplifies access to PublicnEUro datasets
Project-URL: Homepage, https://github.com/datalad/datalad-publicneuro
Project-URL: Documentation, https://github.com/datalad/datalad-publicneuro#readme
Project-URL: Issues, https://github.com/datalad/datalad-publicneuro/issues
Project-URL: Source, https://github.com/datalad/datalad-publicneuro
Project-URL: Changelog, https://github.com/datalad/datalad-publicneuro/blob/main/CHANGELOG.md
Author-email: The DataLad Team and Contributors <team@datalad.org>
License-Expression: MIT
License-File: LICENSE
Keywords: PublicnEUro,datalad,git,git-annex
Classifier: Development Status :: 3 - Alpha
Classifier: Intended Audience :: Developers
Classifier: Intended Audience :: End Users/Desktop
Classifier: License :: OSI Approved :: MIT License
Classifier: Natural Language :: English
Classifier: Operating System :: OS Independent
Classifier: Programming Language :: Python
Classifier: Programming Language :: Python :: 3
Classifier: Programming Language :: Python :: 3.9
Classifier: Programming Language :: Python :: 3.10
Classifier: Programming Language :: Python :: 3.11
Classifier: Programming Language :: Python :: 3.12
Classifier: Programming Language :: Python :: Implementation :: CPython
Classifier: Programming Language :: Python :: Implementation :: PyPy
Classifier: Topic :: Software Development
Classifier: Topic :: Software Development :: Version Control
Classifier: Topic :: Software Development :: Version Control :: Git
Requires-Python: >=3.9
Requires-Dist: annexremote
Requires-Dist: datalad
Requires-Dist: datalad-next
Requires-Dist: datasalad
